tuxipy/__init__.py
tuxipy/tuxi.py
tuxipy-0.0.1.dist-info/LICENSE
tuxipy-0.0.1.dist-info/METADATA
tuxipy-0.0.1.dist-info/WHEEL
tuxipy-0.0.1.dist-info/top_level.txt
tuxipy-0.0.1.dist-info/RECORD
