Metadata-Version: 2.1
Name: tuxipy
Version: 0.0.1
Summary: A CLI tool to scrapes Google search
Home-page: UNKNOWN
Author: DarkMatter-999
Author-email: <darkmatter999official@gmail.com>
License: UNKNOWN
Keywords: python,google,google assistant,search results,assistant,web,web scraping,result scraping,iot,amazon,amazon alexa,google home
Platform: UNKNOWN
Classifier: Development Status :: 1 - Planning
Classifier: Intended Audience :: Developers
Classifier: Programming Language :: Python :: 3
Classifier: Operating System :: Unix
Classifier: Operating System :: MacOS :: MacOS X
Classifier: Operating System :: Microsoft :: Windows
License-File: LICENSE
Requires-Dist: bs4
